download_reels/__init__.py
instareels-0.1.6.dist-info/License.txt
instareels-0.1.6.dist-info/METADATA
instareels-0.1.6.dist-info/WHEEL
instareels-0.1.6.dist-info/top_level.txt
instareels-0.1.6.dist-info/RECORD
