Metadata-Version: 2.1
Name: instareels
Version: 0.1.6
Summary: This can download instagram reels
Home-page: UNKNOWN
Author: @tanay_mishra
Author-email: tanaymishra2204@gmail.com
License: UNKNOWN
Platform: UNKNOWN
Requires-Dist: requests-HTML
Requires-Dist: requests
Requires-Dist: wheel
